YongPythonXueWeijifen/README.md
YongPythonXueWeijifen/__init__.py
YongPythonXueWeijifen/__main__.py
YongPythonXueWeijifen/file.epub
YongPythonXueWeijifen/index.html
YongPythonXueWeijifen/css/__init__.py
YongPythonXueWeijifen/css/annotations.css
YongPythonXueWeijifen/css/main.css
YongPythonXueWeijifen/css/normalize.css
YongPythonXueWeijifen/css/popup.css
YongPythonXueWeijifen/font/__init__.py
YongPythonXueWeijifen/font/fontello.eot
YongPythonXueWeijifen/font/fontello.svg
YongPythonXueWeijifen/font/fontello.ttf
YongPythonXueWeijifen/font/fontello.woff
YongPythonXueWeijifen/img/__init__.py
YongPythonXueWeijifen/img/annotator-glyph-sprite.png
YongPythonXueWeijifen/img/annotator-icon-sprite.png
YongPythonXueWeijifen/img/apple-touch-icon.png
YongPythonXueWeijifen/img/cancelfullscreen.png
YongPythonXueWeijifen/img/close.png
YongPythonXueWeijifen/img/fullscreen.png
YongPythonXueWeijifen/img/loader.gif
YongPythonXueWeijifen/img/menu-icon.png
YongPythonXueWeijifen/img/save.png
YongPythonXueWeijifen/img/saved.png
YongPythonXueWeijifen/img/settings-s.png
YongPythonXueWeijifen/img/settings.png
YongPythonXueWeijifen/img/star.png
YongPythonXueWeijifen/js/__init__.py
YongPythonXueWeijifen/js/epub.js
YongPythonXueWeijifen/js/epub.min.js
YongPythonXueWeijifen/js/epub.min.map
YongPythonXueWeijifen/js/hooks.min.js
YongPythonXueWeijifen/js/hooks.min.map
YongPythonXueWeijifen/js/reader.js
YongPythonXueWeijifen/js/reader.js.map
YongPythonXueWeijifen/js/reader.min.js
YongPythonXueWeijifen/js/reader.min.map
YongPythonXueWeijifen/js/hooks/__init__.py
YongPythonXueWeijifen/js/hooks/extensions/__init__.py
YongPythonXueWeijifen/js/hooks/extensions/highlight.js
YongPythonXueWeijifen/js/libs/__init__.py
YongPythonXueWeijifen/js/libs/jquery.min.js
YongPythonXueWeijifen/js/libs/localforage.min.js
YongPythonXueWeijifen/js/libs/screenfull.js
YongPythonXueWeijifen/js/libs/screenfull.min.js
YongPythonXueWeijifen/js/libs/zip.min.js
YongPythonXueWeijifen/js/plugins/__init__.py
yong_python_xue_weijifen-2024.3.3.0.dist-info/METADATA
yong_python_xue_weijifen-2024.3.3.0.dist-info/WHEEL
yong_python_xue_weijifen-2024.3.3.0.dist-info/entry_points.txt
yong_python_xue_weijifen-2024.3.3.0.dist-info/top_level.txt
yong_python_xue_weijifen-2024.3.3.0.dist-info/RECORD
